<annotation>
	<folder>bridge-6</folder>
	<filename>bridge-6_frame0166.jpg</filename>
	<path>C:\Users\Morgan Taylor\Documents\New folder\intelligent-multi-modal-thermal-visual-traffic-monitoring-system\raw-images\bridge-6\bridge-6_frame0166.jpg</path>
	<source>
		<database>Unknown</database>
	</source>
	<size>
		<width>640</width>
		<height>480</height>
		<depth>3</depth>
	</size>
	<segmented>0</segmented>
	<object>
		<name>heavyTruck</name>
		<pose>Unspecified</pose>
		<truncated>1</truncated>
		<difficult>0</difficult>
		<bndbox>
			<xmin>499</xmin>
			<ymin>114</ymin>
			<xmax>640</xmax>
			<ymax>195</ymax>
		</bndbox>
	</object>
</annotation>
